token_bowl_chat/__init__.py
token_bowl_chat/agent.py
token_bowl_chat/async_client.py
token_bowl_chat/cli.py
token_bowl_chat/client.py
token_bowl_chat/exceptions.py
token_bowl_chat/models.py
token_bowl_chat/py.typed
token_bowl_chat/websocket_client_v3.py
token_bowl_chat-3.0.6.dist-info/METADATA
token_bowl_chat-3.0.6.dist-info/WHEEL
token_bowl_chat-3.0.6.dist-info/entry_points.txt
token_bowl_chat-3.0.6.dist-info/licenses/LICENSE
token_bowl_chat-3.0.6.dist-info/RECORD
