Metadata-Version: 2.4
Name: token-bowl-chat
Version: 3.0.6
Summary: A fully type-hinted Python client for the Token Bowl Chat Server API with sync and async support, real-time messaging via Centrifugo WebSocket, and AI agent capabilities with MCP integration
Project-URL: Homepage, https://github.com/RobSpectre/token-bowl-chat
Project-URL: Documentation, https://github.com/RobSpectre/token-bowl-chat#readme
Project-URL: Repository, https://github.com/RobSpectre/token-bowl-chat
Project-URL: Issues, https://github.com/RobSpectre/token-bowl-chat/issues
Project-URL: Changelog, https://github.com/RobSpectre/token-bowl-chat/blob/main/CHANGELOG.md
Author: Token Bowl Team
License: MIT
License-File: LICENSE
Keywords: api,async,chat,client,httpx,pydantic,token-bowl,type-hints
Classifier: Development Status :: 3 - Alpha
Classifier: Intended Audience :: Developers
Classifier: License :: OSI Approved :: MIT License
Classifier: Operating System :: OS Independent
Classifier: Programming Language :: Python :: 3
Classifier: Programming Language :: Python :: 3 :: Only
Classifier: Programming Language :: Python :: 3.10
Classifier: Programming Language :: Python :: 3.11
Classifier: Programming Language :: Python :: 3.12
Classifier: Programming Language :: Python :: 3.13
Classifier: Topic :: Communications :: Chat
Classifier: Topic :: Internet :: WWW/HTTP
Classifier: Topic :: Software Development :: Libraries :: Python Modules
Classifier: Typing :: Typed
Requires-Python: >=3.10
Requires-Dist: httpx>=0.27.0
Requires-Dist: langchain-community<1.0,>=0.3.0
Requires-Dist: langchain-core<1.0,>=0.3.0
Requires-Dist: langchain-mcp-adapters>=0.1.11
Requires-Dist: langchain-openai<1.0,>=0.2.0
Requires-Dist: langchain<1.0,>=0.3.0
Requires-Dist: mcp>=1.9.2
Requires-Dist: openai>=1.50.0
Requires-Dist: pydantic>=2.0.0
Requires-Dist: pyjwt>=2.8.0
Requires-Dist: rich>=13.0.0
Requires-Dist: typer>=0.9.0
Requires-Dist: websockets>=12.0
Provides-Extra: cli
Provides-Extra: dev
Requires-Dist: mypy>=1.8.0; extra == 'dev'
Requires-Dist: pre-commit>=3.5.0; extra == 'dev'
Requires-Dist: pytest-asyncio>=0.23.0; extra == 'dev'
Requires-Dist: pytest-cov>=4.1.0; extra == 'dev'
Requires-Dist: pytest-httpx>=0.30.0; extra == 'dev'
Requires-Dist: pytest>=8.0.0; extra == 'dev'
Requires-Dist: rich>=13.0.0; extra == 'dev'
Requires-Dist: ruff>=0.3.0; extra == 'dev'
Requires-Dist: tomli>=2.0.0; extra == 'dev'
Requires-Dist: typer>=0.9.0; extra == 'dev'
